olympus_surrogate_bench/__init__.py
olympus_surrogate_bench/api.py
olympus_surrogate_bench/constants.py
olympus_surrogate_bench/data/minimizes.json
olympus_surrogate_bench/data/search_spaces.json
olympus_surrogate_bench/data/alkox/best_config.json
olympus_surrogate_bench/data/alkox/feats.csv
olympus_surrogate_bench/data/alkox/model.pkl
olympus_surrogate_bench/data/alkox/targets.csv
olympus_surrogate_bench/data/benzylation/best_config.json
olympus_surrogate_bench/data/benzylation/feats.csv
olympus_surrogate_bench/data/benzylation/model.pkl
olympus_surrogate_bench/data/benzylation/targets.csv
olympus_surrogate_bench/data/colors_bob/best_config.json
olympus_surrogate_bench/data/colors_bob/feats.csv
olympus_surrogate_bench/data/colors_bob/model.pkl
olympus_surrogate_bench/data/colors_bob/targets.csv
olympus_surrogate_bench/data/colors_n9/best_config.json
olympus_surrogate_bench/data/colors_n9/feats.csv
olympus_surrogate_bench/data/colors_n9/model.pkl
olympus_surrogate_bench/data/colors_n9/targets.csv
olympus_surrogate_bench/data/fullerenes/best_config.json
olympus_surrogate_bench/data/fullerenes/feats.csv
olympus_surrogate_bench/data/fullerenes/model.pkl
olympus_surrogate_bench/data/fullerenes/targets.csv
olympus_surrogate_bench/data/hplc/best_config.json
olympus_surrogate_bench/data/hplc/feats.csv
olympus_surrogate_bench/data/hplc/model.pkl
olympus_surrogate_bench/data/hplc/targets.csv
olympus_surrogate_bench/data/photo_pce10/best_config.json
olympus_surrogate_bench/data/photo_pce10/feats.csv
olympus_surrogate_bench/data/photo_pce10/model.pkl
olympus_surrogate_bench/data/photo_pce10/targets.csv
olympus_surrogate_bench/data/photo_wf3/best_config.json
olympus_surrogate_bench/data/photo_wf3/feats.csv
olympus_surrogate_bench/data/photo_wf3/model.pkl
olympus_surrogate_bench/data/photo_wf3/targets.csv
olympus_surrogate_bench/data/snar/best_config.json
olympus_surrogate_bench/data/snar/feats.csv
olympus_surrogate_bench/data/snar/model.pkl
olympus_surrogate_bench-0.0.2.dist-info/LICENSE
olympus_surrogate_bench-0.0.2.dist-info/METADATA
olympus_surrogate_bench-0.0.2.dist-info/WHEEL
olympus_surrogate_bench-0.0.2.dist-info/top_level.txt
olympus_surrogate_bench-0.0.2.dist-info/RECORD
