Metadata-Version: 2.1
Name: olympus-surrogate-bench
Version: 0.0.2
Home-page: https://github.com/nabenabe0928/olympus-surrogate-bench
Author: nabenabe0928
Author-email: shuhei.watanabe.utokyo@gmail.com
Platform: Linux
Platform: Darwin
Requires-Python: >=3.8
License-File: LICENSE
Requires-Dist: numpy
Requires-Dist: scikit-learn
Requires-Dist: ConfigSpace
Requires-Dist: pandas
